{"version":{"pluginId":"notifications","version":"current","label":"v4","banner":null,"badge":false,"noIndex":false,"className":"docs-version-current","isLast":true,"docsSidebars":{"tutorialSidebar":[{"type":"link","label":"Overview","href":"/docs/notifications/overview","docId":"Overview/index","unlisted":false},{"type":"category","label":"Push Notifications","collapsible":true,"collapsed":true,"items":[{"type":"link","label":"Overview","href":"/docs/notifications/push-overview","docId":"Push Notifications/overview/index","unlisted":false},{"type":"link","label":"Integration","href":"/docs/notifications/push-integration","docId":"Push Notifications/integration/index","unlisted":false},{"type":"link","label":"Customizations","href":"/docs/notifications/push-customization","docId":"Push Notifications/customizations/index","unlisted":false}]},{"type":"category","label":"Email Notifications","collapsible":true,"collapsed":true,"items":[{"type":"link","label":"Overview","href":"/docs/notifications/email-overview","docId":"Email Notifications/Overview/index","unlisted":false},{"type":"link","label":"Integration","href":"/docs/notifications/email-integration","docId":"Email Notifications/Integration/index","unlisted":false},{"type":"link","label":"Customizations","href":"/docs/notifications/email-customization","docId":"Email Notifications/customizations/index","unlisted":false}]},{"type":"category","label":"SMS Notifications","collapsible":true,"collapsed":true,"items":[{"type":"link","label":"Overview","href":"/docs/notifications/sms-overview","docId":"SMS Notifications/Overview/index","unlisted":false},{"type":"link","label":"Integration","href":"/docs/notifications/sms-integration","docId":"SMS Notifications/Integration/index","unlisted":false},{"type":"link","label":"Customizations","href":"/docs/notifications/sms-customization","docId":"SMS Notifications/customizations/index","unlisted":false}]},{"type":"link","label":"Preferences, Templates & Sounds","href":"/docs/notifications/preferences-templates-sounds","docId":"Preferences-templates-sounds/index","unlisted":false},{"type":"category","label":"Legacy Notifications (Extension)","collapsible":true,"collapsed":true,"items":[{"type":"category","label":"Push Notification Extension","collapsible":true,"collapsed":true,"items":[{"type":"link","label":"Web","href":"/docs/notifications/web-push-notifications","docId":"Legacy Notifications (Extension)/push-notifications/javascript/index","unlisted":false},{"type":"link","label":"Android","href":"/docs/notifications/android-push-notifications","docId":"Legacy Notifications (Extension)/push-notifications/android/index","unlisted":false},{"type":"link","label":"Android - Connection Service","href":"/docs/notifications/android-connection-service","docId":"Legacy Notifications (Extension)/push-notifications/android-connection-service/index","unlisted":false},{"type":"link","label":"iOS - FCM","href":"/docs/notifications/ios-fcm-push-notifications","docId":"Legacy Notifications (Extension)/push-notifications/ios-fcm/index","unlisted":false},{"type":"link","label":"iOS - APNs","href":"/docs/notifications/ios-apns-push-notifications","docId":"Legacy Notifications (Extension)/push-notifications/ios-apns/index","unlisted":false},{"type":"link","label":"Flutter","href":"/docs/notifications/flutter-push-notifications","docId":"Legacy Notifications (Extension)/push-notifications/flutter/index","unlisted":false},{"type":"link","label":"React Native","href":"/docs/notifications/react-native-push-notifications","docId":"Legacy Notifications (Extension)/push-notifications/react-native/index","unlisted":false},{"type":"link","label":"Capacitor, Cordova & Ionic","href":"/docs/notifications/capacitor-cordova-ionic-push-notifications","docId":"Legacy Notifications (Extension)/push-notifications/capacitor-cordova-ionic/index","unlisted":false},{"type":"link","label":"Migration Guide","href":"/docs/notifications/migration-guide-push-notifications","docId":"Legacy Notifications (Extension)/push-notifications/migration-guide/index","unlisted":false},{"type":"link","label":"Mute Functionality","href":"/docs/notifications/mute-functionality","docId":"Legacy Notifications (Extension)/push-notifications/mute-functionality/index","unlisted":false},{"type":"link","label":"Token Management","href":"/docs/notifications/token-management","docId":"Legacy Notifications (Extension)/push-notifications/token-management/index","unlisted":false},{"type":"link","label":"Legacy","href":"/docs/notifications/legacy-push-notifications","docId":"Legacy Notifications (Extension)/push-notifications/legacy/index","unlisted":false}],"href":"/docs/notifications/push-notification-extension-overview"},{"type":"link","label":"Email Notification Extension","href":"/docs/notifications/email-notification-extension","docId":"Legacy Notifications (Extension)/email-notifications/index","unlisted":false},{"type":"link","label":"SMS Notification Extension","href":"/docs/notifications/sms-notification-extension","docId":"Legacy Notifications (Extension)/sms-notifications/index","unlisted":false}]}]},"docs":{"Email Notifications/customizations/index":{"id":"Email Notifications/customizations/index","title":"Customizations","description":"Customizations allow controlling notifications for message events, group events, and call events. Users can set preferences for incoming notifications based on notification schedules, Do Not Disturb (DND) mode, and the mute status of specific conversations.","sidebar":"tutorialSidebar"},"Email Notifications/Integration/index":{"id":"Email Notifications/Integration/index","title":"Integration","description":"Pre-requisite","sidebar":"tutorialSidebar"},"Email Notifications/Overview/index":{"id":"Email Notifications/Overview/index","title":"Overview","description":"Introduction","sidebar":"tutorialSidebar"},"Legacy Notifications (Extension)/email-notifications/index":{"id":"Legacy Notifications (Extension)/email-notifications/index","title":"Email Notification Extension","description":"About the extension","sidebar":"tutorialSidebar"},"Legacy Notifications (Extension)/push-notifications/android-connection-service/index":{"id":"Legacy Notifications (Extension)/push-notifications/android-connection-service/index","title":"Android - Connection Service","description":"Learn how to send Push Notifications to your Android app using Firebase Cloud Messaging or FCM.","sidebar":"tutorialSidebar"},"Legacy Notifications (Extension)/push-notifications/android/index":{"id":"Legacy Notifications (Extension)/push-notifications/android/index","title":"Android","description":"The Push Notification extension allows you to send push notifications to mobile apps and desktop browsers.","sidebar":"tutorialSidebar"},"Legacy Notifications (Extension)/push-notifications/capacitor-cordova-ionic/index":{"id":"Legacy Notifications (Extension)/push-notifications/capacitor-cordova-ionic/index","title":"Capacitor, Cordova & Ionic","description":"Learn how to setup Push Notifications for Capacitor, Cordova and Ionic framework using Firebase Cloud Messaging or FCM.","sidebar":"tutorialSidebar"},"Legacy Notifications (Extension)/push-notifications/flutter/index":{"id":"Legacy Notifications (Extension)/push-notifications/flutter/index","title":"Flutter","description":"Learn how to implement Push notifications for the Flutter platform using FCM as well as APNs. This document guides you to set up Flutter push notifications as follows:","sidebar":"tutorialSidebar"},"Legacy Notifications (Extension)/push-notifications/index":{"id":"Legacy Notifications (Extension)/push-notifications/index","title":"Push Notification Extension","description":"Learn how to send push notifications to mobile apps and desktop browsers.","sidebar":"tutorialSidebar"},"Legacy Notifications (Extension)/push-notifications/ios-apns/index":{"id":"Legacy Notifications (Extension)/push-notifications/ios-apns/index","title":"iOS - APNs","description":"Apple Push Notification service or APNs is used to send notifications to iOS devices. With this, you can also use Apple's CallKit for showing the call screen.","sidebar":"tutorialSidebar"},"Legacy Notifications (Extension)/push-notifications/ios-fcm/index":{"id":"Legacy Notifications (Extension)/push-notifications/ios-fcm/index","title":"iOS - FCM","description":"Learn how to send out Push Notifications to your iOS using Firebase Cloud Messaging or FCM.","sidebar":"tutorialSidebar"},"Legacy Notifications (Extension)/push-notifications/javascript/index":{"id":"Legacy Notifications (Extension)/push-notifications/javascript/index","title":"Web","description":"The Push Notification extension allows you to send push notifications to mobile apps and desktop browsers.","sidebar":"tutorialSidebar"},"Legacy Notifications (Extension)/push-notifications/legacy/index":{"id":"Legacy Notifications (Extension)/push-notifications/legacy/index","title":"Legacy","description":"You can check out our new Token-based implementation here.","sidebar":"tutorialSidebar"},"Legacy Notifications (Extension)/push-notifications/migration-guide/index":{"id":"Legacy Notifications (Extension)/push-notifications/migration-guide/index","title":"Migration Guide","description":"Why is Migration required?","sidebar":"tutorialSidebar"},"Legacy Notifications (Extension)/push-notifications/mute-functionality/index":{"id":"Legacy Notifications (Extension)/push-notifications/mute-functionality/index","title":"Mute Functionality","description":"Learn how to enable your users to mute notifications for certain conversations","sidebar":"tutorialSidebar"},"Legacy Notifications (Extension)/push-notifications/react-native/index":{"id":"Legacy Notifications (Extension)/push-notifications/react-native/index","title":"React Native","description":"Learn how to set up Push notifications for React Native using Firebase Cloud Messaging or FCM.","sidebar":"tutorialSidebar"},"Legacy Notifications (Extension)/push-notifications/token-management/index":{"id":"Legacy Notifications (Extension)/push-notifications/token-management/index","title":"Token Management","description":"Register tokens","sidebar":"tutorialSidebar"},"Legacy Notifications (Extension)/sms-notifications/index":{"id":"Legacy Notifications (Extension)/sms-notifications/index","title":"SMS Notification Extension","description":"About the extension","sidebar":"tutorialSidebar"},"Overview/index":{"id":"Overview/index","title":"Overview","description":"Notifications play a crucial role in alerting users to activity within conversations, such as new messages, replies, reactions, and more. CometChat facilitates user engagement through various notification methods, including:","sidebar":"tutorialSidebar"},"Preferences-templates-sounds/index":{"id":"Preferences-templates-sounds/index","title":"Preferences, Templates & Sounds","description":"Common Preferences","sidebar":"tutorialSidebar"},"Push Notifications/customizations/index":{"id":"Push Notifications/customizations/index","title":"Customizations","description":"Customizations allow controlling notifications for message events, group events, and call events. Users can set preferences for incoming notifications based on notification schedules, Do Not Disturb (DND) mode, and the mute status of specific conversations.","sidebar":"tutorialSidebar"},"Push Notifications/integration/index":{"id":"Push Notifications/integration/index","title":"Integration","description":"Enable Push notifications","sidebar":"tutorialSidebar"},"Push Notifications/overview/index":{"id":"Push Notifications/overview/index","title":"Overview","description":"Introduction","sidebar":"tutorialSidebar"},"SMS Notifications/customizations/index":{"id":"SMS Notifications/customizations/index","title":"Customizations","description":"Customizations allow controlling notifications for message events, group events, and call events. Users can set preferences for incoming notifications based on notification schedules, Do Not Disturb (DND) mode, and the mute status of specific conversations.","sidebar":"tutorialSidebar"},"SMS Notifications/Integration/index":{"id":"SMS Notifications/Integration/index","title":"Integration","description":"Pre-requisite","sidebar":"tutorialSidebar"},"SMS Notifications/Overview/index":{"id":"SMS Notifications/Overview/index","title":"Overview","description":"Introduction","sidebar":"tutorialSidebar"}}}}