{
  "id": "resources/4 Remove Delivered Notifications/index",
  "title": "Remove Delivered Notifications",
  "description": "This guide helps you to set up with which you can remove certainly delivered notifications using Notification Service Extension.",
  "source": "@site/ios-chat-sdk_versioned_docs/version-3.0/12-resources/4 Remove Delivered Notifications/index.md",
  "sourceDirName": "12-resources/4 Remove Delivered Notifications",
  "slug": "/remove-delivered-notifications",
  "permalink": "/docs/sdk/ios/3.0/remove-delivered-notifications",
  "draft": false,
  "unlisted": false,
  "tags": [],
  "version": "3.0",
  "lastUpdatedAt": 1539502055000,
  "sidebarPosition": 4,
  "frontMatter": {
    "sidebar_position": 4,
    "title": "Remove Delivered Notifications",
    "slug": "/remove-delivered-notifications"
  },
  "sidebar": "tutorialSidebar",
  "previous": {
    "title": "Upgrading from v2",
    "permalink": "/docs/sdk/ios/3.0/upgrading-from-v2"
  },
  "next": {
    "title": "Launch Call Screen on Tap of Push Notification",
    "permalink": "/docs/sdk/ios/3.0/launch-call-screen-on-tap-of-push-notification"
  }
}