{
  "id": "Messaging/Delivery & Read Rceipts",
  "title": "Delivery & Read Receipts",
  "description": "Mark Messages as Delivered",
  "source": "@site/ionic-chat-sdk_versioned_docs/version-3.0/04-Messaging/11-Delivery & Read Rceipts.md",
  "sourceDirName": "04-Messaging",
  "slug": "/messaging-receipts",
  "permalink": "/docs/sdk/ionic/3.0/messaging-receipts",
  "draft": false,
  "unlisted": false,
  "tags": [],
  "version": "3.0",
  "lastUpdatedAt": 1539502055000,
  "sidebarPosition": 11,
  "frontMatter": {
    "sidebar_position": 11,
    "title": "Delivery & Read Receipts",
    "slug": "/messaging-receipts"
  },
  "sidebar": "tutorialSidebar",
  "previous": {
    "title": "Transient Messages",
    "permalink": "/docs/sdk/ionic/3.0/transient-messages"
  },
  "next": {
    "title": "Calling v3",
    "permalink": "/docs/sdk/ionic/3.0/calling-v3"
  }
}